solar_system_ephemerides/.gitignore
solar_system_ephemerides/__init__.py
solar_system_ephemerides/_version.py
solar_system_ephemerides/ephemeris.py
solar_system_ephemerides/generate.py
solar_system_ephemerides/paths.py
solar_system_ephemerides/ephemerides/__init__.py
solar_system_ephemerides/ephemerides/earth/__init__.py
solar_system_ephemerides/ephemerides/earth/earth00-40-DE200.dat.gz
solar_system_ephemerides/ephemerides/earth/earth00-40-DE405.dat.gz
solar_system_ephemerides/ephemerides/earth/earth00-40-DE421.dat.gz
solar_system_ephemerides/ephemerides/earth/earth00-40-DE430.dat.gz
solar_system_ephemerides/ephemerides/earth/earth00-40-DE435.dat.gz
solar_system_ephemerides/ephemerides/earth/earth00-40-DE436.dat.gz
solar_system_ephemerides/ephemerides/earth/earth00-40-DE440.dat.gz
solar_system_ephemerides/ephemerides/sun/__init__.py
solar_system_ephemerides/ephemerides/sun/sun00-40-DE200.dat.gz
solar_system_ephemerides/ephemerides/sun/sun00-40-DE405.dat.gz
solar_system_ephemerides/ephemerides/sun/sun00-40-DE421.dat.gz
solar_system_ephemerides/ephemerides/sun/sun00-40-DE430.dat.gz
solar_system_ephemerides/ephemerides/sun/sun00-40-DE435.dat.gz
solar_system_ephemerides/ephemerides/sun/sun00-40-DE436.dat.gz
solar_system_ephemerides/ephemerides/sun/sun00-40-DE440.dat.gz
solar_system_ephemerides/ephemerides/time/__init__.py
solar_system_ephemerides/ephemerides/time/tdb_2000-2040.dat.gz
solar_system_ephemerides/ephemerides/time/te405_2000-2040.dat.gz
solar_system_ephemerides/tests/__init__.py
solar_system_ephemerides/tests/test_create_ephemeris.py
solar_system_ephemerides/tests/test_paths.py
solar_system_ephemerides-1.2.0.dist-info/licenses/LICENSE
solar_system_ephemerides-1.2.0.dist-info/METADATA
solar_system_ephemerides-1.2.0.dist-info/WHEEL
solar_system_ephemerides-1.2.0.dist-info/entry_points.txt
solar_system_ephemerides-1.2.0.dist-info/top_level.txt
solar_system_ephemerides-1.2.0.dist-info/RECORD
