Metadata-Version: 2.4
Name: solar_system_ephemerides
Version: 1.2.0
Summary: Solar system ephemeris files
Author-email: Matthew Pitkin <matthew.pitkin@ligo.org>
License: MIT
Project-URL: Source Code, https://git.ligo.org/CW/ephemerides/solar-system-ephemerides
Requires-Python: <4,>=3.9
License-File: LICENSE
Requires-Dist: astropy
Requires-Dist: jplephem
Provides-Extra: test
Requires-Dist: codecov; extra == "test"
Requires-Dist: coverage; extra == "test"
Requires-Dist: coverage-badge; extra == "test"
Requires-Dist: lalsuite; extra == "test"
Requires-Dist: pytest>=4.6; extra == "test"
Requires-Dist: pytest-coverage; extra == "test"
Dynamic: license-file
